ijr/__init__.py
ijr/firefly.py
ijr/gcp_lib.py
ijr/generic_lib.py
ijr/mongo_lib.py
ijr-0.0.22.dist-info/LICENSE
ijr-0.0.22.dist-info/METADATA
ijr-0.0.22.dist-info/WHEEL
ijr-0.0.22.dist-info/top_level.txt
ijr-0.0.22.dist-info/RECORD
