Metadata-Version: 2.1
Name: ijr
Version: 0.0.22
Summary: IJsvogel Package
Home-page: https://github.com/IJsvogel/ijr
Author: IT team IJsvogel Retail
Author-email: it@ijsvogelretail.nl
License: MIT
Platform: UNKNOWN
Requires-Dist: pymongo
Requires-Dist: google-cloud-pubsub
Requires-Dist: google-cloud-secret-manager
